psyc/__init__.py
psyc/main.py
psyc/helpers/__init__.py
psyc/helpers/delete.py
psyc/helpers/edit.py
psyc/helpers/init.py
psyc/helpers/list.py
psyc/helpers/new.py
psyc/helpers/switch.py
psyc-0.1.0.dist-info/LICENSE
psyc-0.1.0.dist-info/METADATA
psyc-0.1.0.dist-info/WHEEL
psyc-0.1.0.dist-info/entry_points.txt
psyc-0.1.0.dist-info/top_level.txt
psyc-0.1.0.dist-info/zip-safe
psyc-0.1.0.dist-info/RECORD
