Metadata-Version: 2.1
Name: psyc
Version: 0.1.0
Summary: PSYC! Parameter Store Your Config
Author: Harvard DCE
License: MIT
License-File: LICENSE
